logilab_common-2.0.0-py3.12-nspkg.pth
logilab/common/__init__.py
logilab/common/cache.py
logilab/common/changelog.py
logilab/common/clcommands.py
logilab/common/compat.py
logilab/common/configuration.py
logilab/common/daemon.py
logilab/common/date.py
logilab/common/debugger.py
logilab/common/decorators.py
logilab/common/deprecation.py
logilab/common/fileutils.py
logilab/common/graph.py
logilab/common/interface.py
logilab/common/logging_ext.py
logilab/common/modutils.py
logilab/common/optik_ext.py
logilab/common/proc.py
logilab/common/py.typed
logilab/common/registry.py
logilab/common/shellutils.py
logilab/common/sphinx_ext.py
logilab/common/sphinxutils.py
logilab/common/table.py
logilab/common/tasksqueue.py
logilab/common/testlib.py
logilab/common/textutils.py
logilab/common/tree.py
logilab/common/types.py
logilab/common/umessage.py
logilab/common/urllib2ext.py
logilab/common/vcgutils.py
logilab/common/visitor.py
logilab/common/xmlutils.py
logilab/common/ureports/__init__.py
logilab/common/ureports/docbook_writer.py
logilab/common/ureports/html_writer.py
logilab/common/ureports/nodes.py
logilab/common/ureports/text_writer.py
logilab_common-2.0.0.data/scripts/logilab-pytest
logilab_common-2.0.0.dist-info/COPYING
logilab_common-2.0.0.dist-info/COPYING.LESSER
logilab_common-2.0.0.dist-info/METADATA
logilab_common-2.0.0.dist-info/WHEEL
logilab_common-2.0.0.dist-info/namespace_packages.txt
logilab_common-2.0.0.dist-info/top_level.txt
logilab_common-2.0.0.dist-info/RECORD
