Metadata-Version: 2.1
Name: logilab-common
Version: 2.0.0
Summary: collection of low-level Python packages and modules used by Logilab projects
Home-page: https://forge.extranet.logilab.fr/open-source/logilab-common
Author: Logilab
Author-email: contact@logilab.fr
License: LGPL
Classifier: Topic :: Utilities
Classifier: Programming Language :: Python
Classifier: Programming Language :: Python :: 3
Classifier: Programming Language :: Python :: 3 :: Only
Requires-Python: >=3.6
License-File: COPYING
License-File: COPYING.LESSER
Requires-Dist: setuptools
Requires-Dist: mypy-extensions
Requires-Dist: typing_extensions
Requires-Dist: importlib_metadata<7,>=6; python_version < "3.10"
